pandasai_sql/__init__.py
pandasai_sql-0.1.6.dist-info/METADATA
pandasai_sql-0.1.6.dist-info/WHEEL
pandasai_sql-0.1.6.dist-info/RECORD
